xyfigure/__init__.py
xyfigure/factory.py
xyfigure/xybase.py
xyfigure/xyfigure.py
xyfigure/xymodel.py
xyfigure/xyview.py
xyfigure/test/__init__.py
xyfigure/test/image_diff.py
xyfigure/test/image_diff_test.py
xyfigure/test/signal_test.py
xyfigure/test/xyfigure_test.py
sibllib-0.0.2.dist-info/LICENSE
sibllib-0.0.2.dist-info/METADATA
sibllib-0.0.2.dist-info/NOTICE.md
sibllib-0.0.2.dist-info/WHEEL
sibllib-0.0.2.dist-info/top_level.txt
sibllib-0.0.2.dist-info/RECORD
